{
    "Line 1": [ 
      "石埠站", "南职院站", "鹏飞路站", "西乡塘客运站", "民族大学站", "清川站", "动物园站", "鲁班路站", "广西大学站（换乘站）", "白苍岭站", "火车站（换乘站）", "朝阳广场站（换乘站）", "新民路站", "民族广场站", "麻村站", "南湖站", "金湖广场站（换乘站）", "会展中心站", "万象城站", "东盟商务区站", "凤岭站", "埌东客运站", "百花岭站", "佛子岭站", "火车东站" 
    ],
    "Line 2": [ 
      "坛泽站", "平良立交站（换乘站）", "那福路站", "玉岭路站", "东风路站", "玉洞站", "金象站", "石子塘站", "建设路站", "大沙田站（换乘站）", "江南客运站", "石柱岭站", "亭洪路站", "福建园站", "南宁剧场站", "朝阳广场站（换乘站）", "火车站（换乘站）", "明秀路站（换乘站）", "秀厢站", "三十三中站", "苏卢站", "安吉客运站（换乘站）", "西津站" 
    ],
    "Line 3": [ 
      "科园大道站", "创业路站", "安吉客运站（换乘站）", "北湖北路站", "秀峰路站", "邕武路站", "大鸡村站", "兴桂路站", "小鸡村站（换乘站）", "东沟岭站", "长堽路站", "东葛路站", "滨湖路站", "金湖广场站（换乘站）", "埌西站", "青竹立交站", "青秀山站", "市博物馆站", "总部基地站（换乘站）", "广西规划馆站", "庆歌路站", "五象湖站", "平良立交站（换乘站）" 
    ],
    "Line 4": [ 
      "洪运路站", "那历村站", "那洪立交站（换乘站）", "金阳路站", "通源路站", "大沙田站（换乘站）", "金象大道站", "五象岭站", "玉象路站", "总部基地站（换乘站）", "飞龙路站", "体育中心西站", "体育中心东站", "良庆大桥南站", "良庆圩站", "楞塘村站" 
    ],
    "Line 5": [ 
      "国凯大道站", "那洪立交站（换乘站）", "金凯路站", "江南公园站", "周家坡站", "五一立交站", "新秀公园站", "广西大学站（换乘站）", "秀灵路站", "明秀路站（换乘站）", "北湖南路站", "虎邱站", "狮山公园站", "小鸡村站（换乘站）", "邕宾立交站", "降桥站", "金桥客运站" 
    ]
  }