{
  "Red Line": [ 
    "Shady Grove Station", "Rockville Station", "Twinbrook Station", "North Bethesda Station", "Grosvenor-Strathmore Station", "Medical Center Station", "Bethesda Station", "Friendship Heights Station", "Tenleytown-AU Station", "Van Ness-UDC Station", "Cleveland Park Station", "Woodley Park Station", "Dupont Circle Station", "Farragut North Station", "Metro Center Station (Transfer Station)", "Gallery Place Station (Transfer Station)", "Judiciary Sq Station", "Union Station Station", "NoMa-Gallaudet U Station", "Rhode Island Ave Station", "Brookland-CUA Station", "Fort Totten Station (Transfer Station)", "Takoma Station", "Silver Spring Station", "Forest Glen Station", "Wheaton Station", "Glenmont Station" 
  ],
  "Orange Line": [ 
    "Vienna Station", "Dunn Loring Station", "West Falls Church Station", "East Falls Church Station (Transfer Station)", "Ballston-MU Station", "Virginia Sq-GMU Station", "Clarendon Station", "Court House Station", "Rosslyn Station (Transfer Station)", "Foggy Bottom-GWU Station", "Farragut West Station", "McPherson Sq Station", "Metro Center Station (Transfer Station)", "Federal Triangle Station", "Smithsonian Station", "L'Enfant Plaza Station (Transfer Station)", "Federal Center SW Station", "Capitol South Station", "Eastern Market Station", "Potomac Ave Station", "Stadium-Armory Station (Transfer Station)", "Minnesota Ave Station", "Deanwood Station", "Cheverly Station", "Landover Station", "New Carrollton Station" 
  ],
  "Blue Line": [ 
    "Franconia-Springfield Station", "Van Dorn St Station", "King St-Old Town Station (Transfer Station)", "Braddock Rd Station", "Potomac Yard Station", "Ronald Reagan Washington National Airport Station", "Crystal City Station", "Pentagon City Station", "Pentagon Station (Transfer Station)", "Arlington Cemetery Station", "Rosslyn Station (Transfer Station)", "Foggy Bottom-GWU Station", "Farragut West Station", "McPherson Sq Station", "Metro Center Station (Transfer Station)", "Federal Triangle Station", "Smithsonian Station", "L'Enfant Plaza Station (Transfer Station)", "Federal Center SW Station", "Capitol South Station", "Eastern Market Station", "Potomac Ave Station", "Stadium-Armory Station (Transfer Station)", "Benning Road Station", "Capitol Heights Station", "Addison Rd Station", "Morgan Blvd Station", "Downtown Largo Station" 
  ],
  "Yellow Line": [ 
    "Huntington Station", "Eisenhower Ave Station", "King St-Old Town Station (Transfer Station)", "Braddock Rd Station", "Potomac Yard Station", "Ronald Reagan Washington National Airport Station", "Crystal City Station", "Pentagon City Station", "Pentagon Station (Transfer Station)", "L'Enfant Plaza Station (Transfer Station)", "Archives Station", "Gallery Place Station (Transfer Station)", "Mt Vernon Sq Station (Transfer Station)" 
  ],
  "Green Line": [ 
    "Branch Ave Station", "Suitland Station", "Naylor Rd Station", "Southern Ave Station", "Congress Heights Station", "Anacostia Station", "Navy Yard-Ballpark Station", "Waterfront Station", "L'Enfant Plaza Station (Transfer Station)", "Archives Station", "Gallery Place Station (Transfer Station)", "Mt Vernon Sq Station (Transfer Station)", "Shaw-Howard U Station", "U St Station", "Columbia Heights Station", "Georgia Ave-Petworth Station", "Fort Totten Station (Transfer Station)", "West Hyattsville Station", "Hyattsville Crossing Station", "College Park-U of Md Station", "Greenbelt Station" 
  ],
  "Silver Line": [ 
    "Ashburn Station", "Loudoun Gateway Station", "Washington Dulles International Airport Station", "Innovation Center Station", "Herndon Station", "Reston Town Center Station", "Wiehle-Reston East Station", "Spring Hill Station", "Greensboro Station", "Tysons Station", "McLean Station", "East Falls Church Station (Transfer Station)", "Ballston-MU Station", "Virginia Sq-GMU Station", "Clarendon Station", "Court House Station", "Rosslyn Station (Transfer Station)", "Foggy Bottom-GWU Station", "Farragut West Station", "McPherson Sq Station", "Metro Center Station (Transfer Station)", "Federal Triangle Station", "Smithsonian Station", "L'Enfant Plaza Station (Transfer Station)", "Federal Center SW Station", "Capitol South Station", "Eastern Market Station", "Potomac Ave Station", "Stadium-Armory Station (Transfer Station)", "Benning Road Station", "Capitol Heights Station", "Addison Rd Station", "Morgan Blvd Station", "Downtown Largo Station" 
  ]
}